lserest/__init__.py
lserest/_util.py
lserest/lse_client.py
lserest/model_application.py
lserest/nitrosamine_assessment.py
lserest/structure_search.py
lserest/structure_set.py
lserest-1.2.0.dist-info/LICENSE
lserest-1.2.0.dist-info/METADATA
lserest-1.2.0.dist-info/WHEEL
lserest-1.2.0.dist-info/top_level.txt
lserest-1.2.0.dist-info/RECORD
