Metadata-Version: 2.1
Name: lserest
Version: 1.2.0
Summary: Provides access to Leadscope Web Services REST API via Python.
Author: Chris Miles, Scott Miller, Leadscope Inc., Instem LSS Ltd.
Author-email: chris.miles@instem.com
Project-URL: Documentation, https://leadscope-support.instem.com/ls-manuals/lse_rest_api/
Classifier: Programming Language :: Python :: 3
Classifier: License :: OSI Approved :: Apache Software License
Classifier: Operating System :: OS Independent
Requires-Python: >=3.7
License-File: LICENSE
Requires-Dist: pandas
Requires-Dist: requests
Requires-Dist: tomli
